nanimsave/__init__.py
nanimsave-0.1.dist-info/LICENSE
nanimsave-0.1.dist-info/METADATA
nanimsave-0.1.dist-info/WHEEL
nanimsave-0.1.dist-info/top_level.txt
nanimsave-0.1.dist-info/RECORD
